isne_recommendation/FeatureRatingsKNN.py
isne_recommendation/Hybrid.py
isne_recommendation/TfidfLinearKernel.py
isne_recommendation/__init__.py
isne_recommendation-0.1.3.dist-info/METADATA
isne_recommendation-0.1.3.dist-info/WHEEL
isne_recommendation-0.1.3.dist-info/licenses/LICENSE
isne_recommendation-0.1.3.dist-info/RECORD
