Metadata-Version: 2.3
Name: isne-recommendation
Version: 0.1.3
Summary: The recommendation system aims to suggest the best suitable courses for learners who have taken at least one course.
Project-URL: Homepage, https://github.com/startg2545/recommendation-system
Project-URL: Issues, https://github.com/startg2545/recommendation-system/issues
Author-email: Newin Yamaguchi <newin_yamaguchi@cmu.ac.th>
License-File: LICENSE
Classifier: License :: OSI Approved :: MIT License
Classifier: Operating System :: OS Independent
Classifier: Programming Language :: Python :: 3
Requires-Python: >=3.8
Requires-Dist: fuzzywuzzy==0.18.0
Requires-Dist: joblib==1.3.2
Requires-Dist: levenshtein==0.25.0
Requires-Dist: numpy==1.26.4
Requires-Dist: openpyxl==3.1.2
Requires-Dist: pandas==1.5.3
Requires-Dist: python-dateutil==2.9.0.post0
Requires-Dist: python-levenshtein==0.25.0
Requires-Dist: pytz==2024.1
Requires-Dist: rapidfuzz==3.6.2
Requires-Dist: scikit-learn==1.4.1.post1
Requires-Dist: scipy==1.12.0
Requires-Dist: six==1.16.0
Requires-Dist: threadpoolctl==3.3.0
Requires-Dist: tzdata==2024.1
